wombat/utils/__init__.py
wombat/utils/dictionary.py
wombat/utils/errors/decorators.py
wombat/utils/errors/exceptions.py
wombat/utils/files/search.py
wombat_utils-0.2.6.dist-info/METADATA
wombat_utils-0.2.6.dist-info/WHEEL
wombat_utils-0.2.6.dist-info/RECORD
