Metadata-Version: 2.4
Name: wombat-utils
Version: 0.2.6
Summary: Various utilities for making python development easier
Project-URL: Homepage, https://github.com/RLC92/wombat-utils
Project-URL: Issues, https://github.com/RLC92/wombat-utils/issues
Requires-Python: >=3.11.11
Requires-Dist: pydantic>=2.9.2
Requires-Dist: type-lens>=0.2.3
